<?xml version="1.0" encoding="utf-8"?>
<images>
  <image>
      <url>pics/img_1.png</url>
  </image>
  <image>
      <url>pics/img_2.png</url>
  </image>
  <image>
      <url>pics/img_3.png</url>
  </image>
  <image>
      <url>pics/img_4.png</url>
  </image>
  <image>
      <url>pics/img_5.png</url>
  </image>
  <image>
      <url>pics/img_6.png</url>
  </image>
  <image>
      <url>pics/img_7.png</url>
  </image>
  <image>
      <url>pics/img_8.png</url>
  </image>
  <image>
      <url>pics/img_9.png</url>
  </image>
  <image>
      <url>pics/img_10.png</url>
  </image>
  <image>
      <url>pics/img_11.png</url>
  </image>
  <image>
      <url>pics/img_12.png</url>
  </image>
  <image>
      <url>pics/img_13.png</url>
  </image>
  <image>
      <url>pics/img_14.png</url>
  </image>
  <image>
      <url>pics/img_15.png</url>
  </image>
</images>
